HuibianyuyanRumenjiaochengCYuyanBianchengWang/README.md
HuibianyuyanRumenjiaochengCYuyanBianchengWang/__init__.py
HuibianyuyanRumenjiaochengCYuyanBianchengWang/__main__.py
HuibianyuyanRumenjiaochengCYuyanBianchengWang/file.epub
HuibianyuyanRumenjiaochengCYuyanBianchengWang/index.html
HuibianyuyanRumenjiaochengCYuyanBianchengWang/css/__init__.py
HuibianyuyanRumenjiaochengCYuyanBianchengWang/css/annotations.css
HuibianyuyanRumenjiaochengCYuyanBianchengWang/css/main.css
HuibianyuyanRumenjiaochengCYuyanBianchengWang/css/normalize.css
HuibianyuyanRumenjiaochengCYuyanBianchengWang/css/popup.css
HuibianyuyanRumenjiaochengCYuyanBianchengWang/font/__init__.py
HuibianyuyanRumenjiaochengCYuyanBianchengWang/font/fontello.eot
HuibianyuyanRumenjiaochengCYuyanBianchengWang/font/fontello.svg
HuibianyuyanRumenjiaochengCYuyanBianchengWang/font/fontello.ttf
HuibianyuyanRumenjiaochengCYuyanBianchengWang/font/fontello.woff
HuibianyuyanRumenjiaochengCYuyanBianchengWang/img/__init__.py
HuibianyuyanRumenjiaochengCYuyanBianchengWang/img/annotator-glyph-sprite.png
HuibianyuyanRumenjiaochengCYuyanBianchengWang/img/annotator-icon-sprite.png
HuibianyuyanRumenjiaochengCYuyanBianchengWang/img/apple-touch-icon.png
HuibianyuyanRumenjiaochengCYuyanBianchengWang/img/cancelfullscreen.png
HuibianyuyanRumenjiaochengCYuyanBianchengWang/img/close.png
HuibianyuyanRumenjiaochengCYuyanBianchengWang/img/fullscreen.png
HuibianyuyanRumenjiaochengCYuyanBianchengWang/img/loader.gif
HuibianyuyanRumenjiaochengCYuyanBianchengWang/img/menu-icon.png
HuibianyuyanRumenjiaochengCYuyanBianchengWang/img/save.png
HuibianyuyanRumenjiaochengCYuyanBianchengWang/img/saved.png
HuibianyuyanRumenjiaochengCYuyanBianchengWang/img/settings-s.png
HuibianyuyanRumenjiaochengCYuyanBianchengWang/img/settings.png
HuibianyuyanRumenjiaochengCYuyanBianchengWang/img/star.png
HuibianyuyanRumenjiaochengCYuyanBianchengWang/js/__init__.py
HuibianyuyanRumenjiaochengCYuyanBianchengWang/js/epub.js
huibianyuyan_rumenjiaocheng_c_yuyan_biancheng_wang-2024.3.4.0.dist-info/METADATA
huibianyuyan_rumenjiaocheng_c_yuyan_biancheng_wang-2024.3.4.0.dist-info/WHEEL
huibianyuyan_rumenjiaocheng_c_yuyan_biancheng_wang-2024.3.4.0.dist-info/entry_points.txt
huibianyuyan_rumenjiaocheng_c_yuyan_biancheng_wang-2024.3.4.0.dist-info/top_level.txt
huibianyuyan_rumenjiaocheng_c_yuyan_biancheng_wang-2024.3.4.0.dist-info/RECORD
